{"label":"Tasks for ~/Projects/network-ai/tasks/combine.js","nodes":[{"label":"default","type":"task","nodes":[{"label":"<series>","type":"function","branch":true,"nodes":[{"label":"<series>","type":"function","branch":true,"nodes":[{"label":"clean","type":"function","nodes":[]},{"label":"<parallel>","type":"function","branch":true,"nodes":[{"label":"js","type":"function","nodes":[]},{"label":"css","type":"function","nodes":[]},{"label":"img","type":"function","nodes":[]}]},{"label":"deploy","type":"function","nodes":[]}]},{"label":"<series>","type":"function","branch":true,"nodes":[{"label":"train","type":"function","nodes":[]},{"label":"generate","type":"function","nodes":[]},{"label":"log","type":"function","nodes":[]}]}]}]}]}
